AUTHORS
LICENSE
MANIFEST.in
README.rst
setup.py
django_uploadstatic.egg-info/PKG-INFO
django_uploadstatic.egg-info/SOURCES.txt
django_uploadstatic.egg-info/dependency_links.txt
django_uploadstatic.egg-info/not-zip-safe
django_uploadstatic.egg-info/top_level.txt
uploadstatic/__init__.py
uploadstatic/models.py
uploadstatic/test_settings.py
uploadstatic/utils.py
uploadstatic/management/__init__.py
uploadstatic/management/commands/__init__.py
uploadstatic/management/commands/uploadstatic.py
uploadstatic/tests/__init__.py
uploadstatic/tests/models.py
uploadstatic/tests/storage.py
uploadstatic/tests/tests.py
uploadstatic/tests/apps/__init__.py
uploadstatic/tests/apps/test/__init__.py
uploadstatic/tests/apps/test/models.py
uploadstatic/tests/apps/test/otherdir/odfile.txt
uploadstatic/tests/apps/test/static/test/CVS
uploadstatic/tests/apps/test/static/test/file.txt
uploadstatic/tests/apps/test/static/test/file1.txt
uploadstatic/tests/apps/test/static/test/test.ignoreme
uploadstatic/tests/apps/test/static/test/test_absolute.ignoreme3
uploadstatic/tests/apps/test/static/test/test_relative.ignoreme2
uploadstatic/tests/project/documents/test.txt
uploadstatic/tests/project/documents/cached/absolute.css
uploadstatic/tests/project/documents/cached/denorm.css
uploadstatic/tests/project/documents/cached/other.css
uploadstatic/tests/project/documents/cached/relative.css
uploadstatic/tests/project/documents/cached/styles.css
uploadstatic/tests/project/documents/cached/url.css
uploadstatic/tests/project/documents/cached/css/fragments.css
uploadstatic/tests/project/documents/cached/css/window.css
uploadstatic/tests/project/documents/cached/css/fonts/font.eot
uploadstatic/tests/project/documents/cached/css/fonts/font.svg
uploadstatic/tests/project/documents/cached/css/img/window.png
uploadstatic/tests/project/documents/cached/img/relative.png
uploadstatic/tests/project/documents/ignored/test_directory.txt
uploadstatic/tests/project/documents/subdir/test.txt
uploadstatic/tests/project/documents/test/camelCase.txt
uploadstatic/tests/project/documents/test/file.txt
uploadstatic/tests/project/documents/test/test.ignoreme4
uploadstatic/tests/project/documents/test/test_absolute.ignoreme6
