Metadata-Version: 1.1
Name: django-uploadstatic
Version: 0.2.1
Summary: A Django app that provides helpers for uploading static files.
Home-page: http://github.com/streeter/django-uploadstatic
Author: Chris Streeter
Author-email: chris@chrisstreeter.com
License: BSD
Platform: UNKNOWN
Classifier: Development Status :: 5 - Production/Stable
Classifier: Environment :: Web Environment
Classifier: Intended Audience :: Developers
Classifier: License :: OSI Approved :: BSD License
Classifier: Operating System :: OS Independent
Classifier: Programming Language :: Python
Classifier: Programming Language :: Python :: 2.5
Classifier: Programming Language :: Python :: 2.6
Classifier: Programming Language :: Python :: 2.7
Classifier: Framework :: Django
